README.rst
setup.py
PyGoogleVoice.egg-info/PKG-INFO
PyGoogleVoice.egg-info/SOURCES.txt
PyGoogleVoice.egg-info/dependency_links.txt
PyGoogleVoice.egg-info/requires.txt
PyGoogleVoice.egg-info/top_level.txt
bin/asterisk-gvoice-setup
bin/gvi
bin/gvoice
googlevoice/__init__.py
googlevoice/conf.py
googlevoice/settings.py
googlevoice/tests.py
googlevoice/util.py
googlevoice/voice.py