Metadata-Version: 1.0
Name: PyGoogleVoice
Version: 0.5.2
Summary: Python 2/3 Interface for Google Voice
Home-page: https://bitbucket.org/tom_slick/pygooglevoice
Author: Tom Enos
Author-email: tomslick.ca@gmail.com
License: UNKNOWN
Platform: UNKNOWN
